connexion/extended/aiohttp.py
connexion/extended/base.py
connexion/extended/flask.py
connexion_auth_paths_extd-0.0.6.dist-info/LICENSE
connexion_auth_paths_extd-0.0.6.dist-info/METADATA
connexion_auth_paths_extd-0.0.6.dist-info/WHEEL
connexion_auth_paths_extd-0.0.6.dist-info/top_level.txt
connexion_auth_paths_extd-0.0.6.dist-info/RECORD
