Metadata-Version: 2.1
Name: connexion-auth-paths-extd
Version: 0.0.6
Summary: Small connexion extension to add authentication into spec routes
Home-page: https://github.com/exageraldo/connexion-auth-paths-extd
Author: Geraldo Castro
Author-email: victormatheuscastro@gmail.com
License: BSD-3-Clause
Project-URL: Bug Tracker, https://github.com/exageraldo/connexion-auth-paths-extd/issues
Platform: UNKNOWN
Classifier: Development Status :: 4 - Beta
Classifier: Intended Audience :: Developers
Classifier: License :: OSI Approved :: BSD License
Classifier: Operating System :: OS Independent
Classifier: Programming Language :: Python
Classifier: Programming Language :: Python :: 3
Classifier: Programming Language :: Python :: 3.6
Classifier: Programming Language :: Python :: 3.7
Classifier: Programming Language :: Python :: 3.8
Classifier: Topic :: Software Development :: Libraries :: Python Modules
Classifier: Topic :: Software Development :: Libraries :: Application Frameworks
Requires-Dist: connexion
Provides-Extra: aiohttp
Requires-Dist: connexion[aiohttp] ; extra == 'aiohttp'
